generate_thumbnail/Arguments.py
generate_thumbnail/__init__.py
generate_thumbnail/decorators.py
generate_thumbnail/generate_gifnail.py
generate_thumbnail/generate_thumbnail.py
king_caesar-0.0.3.dist-info/METADATA
king_caesar-0.0.3.dist-info/WHEEL
king_caesar-0.0.3.dist-info/top_level.txt
king_caesar-0.0.3.dist-info/RECORD
