Metadata-Version: 2.1
Name: king-caesar
Version: 0.0.3
Summary: video thumbnails generator
Home-page: https://github.com/murilo-bracero/generate_thumbnail
Author: Murilo Amais Bracero
Author-email: murilobracero@gmail.com
License: MIT
Keywords: generator generate thumbnail
Platform: UNKNOWN
Classifier: Programming Language :: Python :: 3
Classifier: License :: OSI Approved :: MIT License
Classifier: Operating System :: OS Independent
Requires-Python: >=3.6
Requires-Dist: opencv-python
Requires-Dist: imageio
